.DS_Store
pypiLearn/__init__.py
pypiLearn/__main__.py
pypiLearn/test.py
pypiLearn-0.0.2.dist-info/LICENSE
pypiLearn-0.0.2.dist-info/METADATA
pypiLearn-0.0.2.dist-info/WHEEL
pypiLearn-0.0.2.dist-info/top_level.txt
pypiLearn-0.0.2.dist-info/RECORD
